{
  "CorrelationData" : [
    {"author":";作者: 王敏;周才平;","id":1,"title":"山地植物群落数量分类和排序研究进展"},
    {"author":";作者: 朱春华;林甦;陈珍;刘斌琼;万春和;傅光华;黄瑜;","id":2,"title":"福建省禽流感病毒非结构蛋白基因特征分析"},
    {"author":";作者: 包红梅;赵玉辉;李一经;王秀荣;陈化兰;","id":3,"title":"H7亚型禽流感病毒RT-LAMP快速检测方法的建立"},
    {"author":";作者: 吴光,何和明","id":4,"title":"绞股蓝植株水分生理变化的研究"},
    {"author":";作者: 黄轩;","id":5,"title":"光照因素对家禽生产的影响"},
    {"author":";作者: 程须珍,杨又迪","id":6,"title":"RAPD分析在绿豆亲缘关系研究中的应用"},
    {"author":";作者: 沈丽,张琳,南燕","id":7,"title":"体视学在突触超微结构定量研究中的应用"},
    {"author":";作者: 陈鹏;肖瑞;梁洁;马萍;单清;王长振;康宏向;高荣莲;钱焕文;","id":8,"title":"HPM长期辐照的眼生物效应研究"},
    {"author":";作者: 何萍;丁云芳;","id":9,"title":"铜绿假单胞菌耐药机制的研究进展"}
  ]
}
